<annotation>
	<folder>wba-15196-000-c008</folder>
	<filename>1049-wba-15196-000-c008-1573543165-shelf5.jpg</filename>
	<path>C:\Users\ykuma\Documents\15196\wba-15196-000-c008\1049-wba-15196-000-c008-1573543165-shelf5.jpg</path>
	<source>
		<database>Unknown</database>
	</source>
	<size>
		<width>900</width>
		<height>400</height>
		<depth>3</depth>
	</size>
	<segmented>0</segmented>
	<object>
		<name>bottle</name>
		<pose>Unspecified</pose>
		<truncated>0</truncated>
		<difficult>0</difficult>
		<bndbox>
			<xmin>208</xmin>
			<ymin>102</ymin>
			<xmax>248</xmax>
			<ymax>336</ymax>
		</bndbox>
	</object>
	<object>
		<name>bottle</name>
		<pose>Unspecified</pose>
		<truncated>0</truncated>
		<difficult>0</difficult>
		<bndbox>
			<xmin>251</xmin>
			<ymin>98</ymin>
			<xmax>312</xmax>
			<ymax>351</ymax>
		</bndbox>
	</object>
	<object>
		<name>bottle</name>
		<pose>Unspecified</pose>
		<truncated>0</truncated>
		<difficult>0</difficult>
		<bndbox>
			<xmin>340</xmin>
			<ymin>109</ymin>
			<xmax>403</xmax>
			<ymax>357</ymax>
		</bndbox>
	</object>
	<object>
		<name>bottle</name>
		<pose>Unspecified</pose>
		<truncated>0</truncated>
		<difficult>0</difficult>
		<bndbox>
			<xmin>545</xmin>
			<ymin>64</ymin>
			<xmax>631</xmax>
			<ymax>374</ymax>
		</bndbox>
	</object>
	<object>
		<name>bottle</name>
		<pose>Unspecified</pose>
		<truncated>0</truncated>
		<difficult>0</difficult>
		<bndbox>
			<xmin>638</xmin>
			<ymin>146</ymin>
			<xmax>722</xmax>
			<ymax>369</ymax>
		</bndbox>
	</object>
</annotation>