<annotation>
	<folder>wba-15196-000-c025</folder>
	<filename>3083-wba-15196-000-c025-1573547398-shelf2.jpg</filename>
	<path>/home/qwinix/Documents/15196/wba-15196-000-c025/3083-wba-15196-000-c025-1573547398-shelf2.jpg</path>
	<source>
		<database>Unknown</database>
	</source>
	<size>
		<width>900</width>
		<height>400</height>
		<depth>3</depth>
	</size>
	<segmented>0</segmented>
	<object>
		<name>bottle</name>
		<pose>Unspecified</pose>
		<truncated>1</truncated>
		<difficult>0</difficult>
		<bndbox>
			<xmin>39</xmin>
			<ymin>1</ymin>
			<xmax>214</xmax>
			<ymax>356</ymax>
		</bndbox>
	</object>
	<object>
		<name>bottle</name>
		<pose>Unspecified</pose>
		<truncated>1</truncated>
		<difficult>0</difficult>
		<bndbox>
			<xmin>357</xmin>
			<ymin>1</ymin>
			<xmax>505</xmax>
			<ymax>354</ymax>
		</bndbox>
	</object>
	<object>
		<name>bottle</name>
		<pose>Unspecified</pose>
		<truncated>0</truncated>
		<difficult>0</difficult>
		<bndbox>
			<xmin>509</xmin>
			<ymin>113</ymin>
			<xmax>651</xmax>
			<ymax>339</ymax>
		</bndbox>
	</object>
	<object>
		<name>bottle</name>
		<pose>Unspecified</pose>
		<truncated>0</truncated>
		<difficult>0</difficult>
		<bndbox>
			<xmin>643</xmin>
			<ymin>81</ymin>
			<xmax>727</xmax>
			<ymax>254</ymax>
		</bndbox>
	</object>
	<object>
		<name>bottle</name>
		<pose>Unspecified</pose>
		<truncated>0</truncated>
		<difficult>0</difficult>
		<bndbox>
			<xmin>796</xmin>
			<ymin>101</ymin>
			<xmax>898</xmax>
			<ymax>313</ymax>
		</bndbox>
	</object>
	<object>
		<name>bottle</name>
		<pose>Unspecified</pose>
		<truncated>1</truncated>
		<difficult>0</difficult>
		<bndbox>
			<xmin>287</xmin>
			<ymin>1</ymin>
			<xmax>358</xmax>
			<ymax>266</ymax>
		</bndbox>
	</object>
</annotation>