<annotation>
	<folder>wba-15196-000-c025</folder>
	<filename>3206-wba-15196-000-c025-1573547658-shelf1.jpg</filename>
	<path>/home/qwinix/Documents/15196/wba-15196-000-c025/3206-wba-15196-000-c025-1573547658-shelf1.jpg</path>
	<source>
		<database>Unknown</database>
	</source>
	<size>
		<width>900</width>
		<height>400</height>
		<depth>3</depth>
	</size>
	<segmented>0</segmented>
	<object>
		<name>bottle</name>
		<pose>Unspecified</pose>
		<truncated>0</truncated>
		<difficult>0</difficult>
		<bndbox>
			<xmin>180</xmin>
			<ymin>71</ymin>
			<xmax>324</xmax>
			<ymax>362</ymax>
		</bndbox>
	</object>
	<object>
		<name>bottle</name>
		<pose>Unspecified</pose>
		<truncated>0</truncated>
		<difficult>0</difficult>
		<bndbox>
			<xmin>113</xmin>
			<ymin>125</ymin>
			<xmax>175</xmax>
			<ymax>365</ymax>
		</bndbox>
	</object>
	<object>
		<name>bottle</name>
		<pose>Unspecified</pose>
		<truncated>0</truncated>
		<difficult>0</difficult>
		<bndbox>
			<xmin>326</xmin>
			<ymin>157</ymin>
			<xmax>467</xmax>
			<ymax>361</ymax>
		</bndbox>
	</object>
	<object>
		<name>bottle</name>
		<pose>Unspecified</pose>
		<truncated>0</truncated>
		<difficult>0</difficult>
		<bndbox>
			<xmin>473</xmin>
			<ymin>161</ymin>
			<xmax>675</xmax>
			<ymax>364</ymax>
		</bndbox>
	</object>
	<object>
		<name>bottle</name>
		<pose>Unspecified</pose>
		<truncated>0</truncated>
		<difficult>0</difficult>
		<bndbox>
			<xmin>679</xmin>
			<ymin>158</ymin>
			<xmax>869</xmax>
			<ymax>359</ymax>
		</bndbox>
	</object>
</annotation>